RefraModel/__init__.py
RefraModel/__main__.py
RefraModel/main.py
RefraModel/model_builder.py
RefraModel/version.py
RefraModel/editors/body_editor.py
RefraModel/editors/node_editor.py
RefraModel/editors/property_editor.py
RefraModel/geometry/bodies.py
RefraModel/geometry/lines.py
RefraModel/geometry/points.py
RefraModel/inversion/forward_model.py
RefraModel/inversion/inversion.py
RefraModel/inversion/mesh_builder.py
RefraModel/ui/dialogs.py
RefraModel/ui/menu.py
RefraModel/ui/plot_manager.py
RefraModel/utils/file_io.py
RefraModel/utils/geometry_utils.py
reframodel-2026.1.3.dist-info/licenses/LICENSE
reframodel-2026.1.3.dist-info/METADATA
reframodel-2026.1.3.dist-info/WHEEL
reframodel-2026.1.3.dist-info/entry_points.txt
reframodel-2026.1.3.dist-info/top_level.txt
reframodel-2026.1.3.dist-info/RECORD
